my_python_package/__init__.py
my_python_package/phenome_gen.py
my_python_package/test.py
telugu_phenome_gen-0.1.0.dist-info/METADATA
telugu_phenome_gen-0.1.0.dist-info/WHEEL
telugu_phenome_gen-0.1.0.dist-info/top_level.txt
telugu_phenome_gen-0.1.0.dist-info/RECORD
