Metadata-Version: 2.1
Name: telugu_phenome_gen
Version: 0.1.0
Summary: A package for converting Telugu text to phonetic representations in English.
Home-page: https://github.com/RAVINDRA8008/TELUGU-PHENOME-TO-ENGLISH
Author: RAVINDRA CHOWDARY JONNAGADLA
Classifier: Programming Language :: Python :: 3
Classifier: License :: OSI Approved :: MIT License
Classifier: Operating System :: OS Independent
Requires-Python: >=3.6
